AUTHORS.txt
LICENSE.txt
MANIFEST.in
loraExample_config.ini
loraExample_relayServer.py
loraExample_testclient.py
setup.py
LoraDecoder.egg-info/PKG-INFO
LoraDecoder.egg-info/SOURCES.txt
LoraDecoder.egg-info/dependency_links.txt
LoraDecoder.egg-info/not-zip-safe
LoraDecoder.egg-info/requires.txt
LoraDecoder.egg-info/top_level.txt
loradecoder/__init__.py
loradecoder/loraExceptions.py
loradecoder/loraPacketDecoder.py
loradecoder/loraPayLoad.py