Metadata-Version: 1.1
Name: LoraDecoder
Version: 0.1.0
Summary: LoRaWan1.0 packet decoder
Home-page: https://github.com/Timvandervoord/LoraDecoder.git
Author: timvandervoord
Author-email: timvandervoord@gmail.com
License: GNU
Platform: any
Classifier: Environment :: Web Environment
Classifier: Intended Audience :: Developers
Classifier: License :: OSI Approved :: GNU General Public License v3 (GPLv3) 
Classifier: Operating System :: OS Independent
Classifier: Programming Language :: Python
Classifier: Programming Language :: Python :: 2
Classifier: Programming Language :: Python :: 3
Classifier: Topic :: Internet :: WWW/HTTP :: Dynamic Content
Classifier: Topic :: Software Development :: Libraries :: Python Modules
